selfie_lib/ArrayMap.py
selfie_lib/Atomic.py
selfie_lib/CacheSelfie.py
selfie_lib/CommentTracker.py
selfie_lib/ConvertToWindowsNewlines.py
selfie_lib/EscapeLeadingWhitespace.py
selfie_lib/FS.py
selfie_lib/Lens.py
selfie_lib/LineReader.py
selfie_lib/Literals.py
selfie_lib/ParseException.py
selfie_lib/PerCharacterEscaper.py
selfie_lib/Roundtrip.py
selfie_lib/Selfie.py
selfie_lib/SelfieImplementations.py
selfie_lib/Slice.py
selfie_lib/Snapshot.py
selfie_lib/SnapshotFile.py
selfie_lib/SnapshotReader.py
selfie_lib/SnapshotSystem.py
selfie_lib/SnapshotValue.py
selfie_lib/SnapshotValueReader.py
selfie_lib/SourceFile.py
selfie_lib/TypedPath.py
selfie_lib/WithinTestGC.py
selfie_lib/WriteTracker.py
selfie_lib/__init__.py
selfie_lib-1.0.0.dist-info/METADATA
selfie_lib-1.0.0.dist-info/WHEEL
selfie_lib-1.0.0.dist-info/top_level.txt
selfie_lib-1.0.0.dist-info/RECORD
