Metadata-Version: 2.1
Name: selfie-lib
Version: 1.0.0
Summary: Infrastructure for creating selfie-compatible test runner plugins.
Author-email: Edwin Ye <EdwinYeDeveloper@gmail.com>, Harvir Sahota <hsahota2312@gmail.com>, Ned Twigg <ned.twigg@diffplug.com>, Selina Delgado <sdelgado411@gmail.com>
License: Apache-2.0
Requires-Python: >=3.9
